command/__init__.py
gradle/__init__.py
gradle/command.py
gradle/error.py
gradle/project.py
java/__init__.py
java/blob.py
minecraft/__init__.py
minecraft/source.py
minecraft/version.py
mint/__init__.py
mint/error.py
mint/repo.py
shulkr/__init__.py
shulkr/__main__.py
shulkr/app.py
shulkr/cli.py
shulkr/compatibility.py
shulkr/config.py
shulkr/gitignore.py
shulkr/repo.py
shulkr/version.py
shulkr-0.7.2.dist-info/LICENSE
shulkr-0.7.2.dist-info/METADATA
shulkr-0.7.2.dist-info/WHEEL
shulkr-0.7.2.dist-info/entry_points.txt
shulkr-0.7.2.dist-info/top_level.txt
shulkr-0.7.2.dist-info/RECORD
