Metadata-Version: 2.1
Name: shulkr
Version: 0.7.2
Summary: Diff decompiled versions of Minecraft
Home-page: https://github.com/clabe45/shulkr
Author: Caleb Sacks
License: GPLv3
Keywords: minecraft,git,decompile,game
Classifier: Development Status :: 3 - Alpha
Classifier: Environment :: Console
Classifier: Intended Audience :: Developers
Classifier: Intended Audience :: Science/Research
Classifier: License :: OSI Approved :: Apache Software License
Classifier: Operating System :: OS Independent
Classifier: Programming Language :: Python
Classifier: Programming Language :: Python :: 3
Classifier: Topic :: Games/Entertainment
Classifier: Topic :: Scientific/Engineering
Classifier: Topic :: Software Development :: Version Control :: Git
Classifier: Topic :: Utilities
License-File: LICENSE
Requires-Dist: gitpython
Requires-Dist: javalang
Requires-Dist: unidiff
Requires-Dist: requests
Requires-Dist: toml
Requires-Dist: click
